LICENSE
MANIFEST.in
README.md
setup.py
module_graph/__init__.py
module_graph/hooker.py
module_graph/main.py
module_graph/render.py
module_graph/run_traveler.py
module_graph/traveler.py
module_graph.egg-info/PKG-INFO
module_graph.egg-info/SOURCES.txt
module_graph.egg-info/dependency_links.txt
module_graph.egg-info/entry_points.txt
module_graph.egg-info/requires.txt
module_graph.egg-info/top_level.txt