Metadata-Version: 2.1
Name: module-graph
Version: 0.0.1
Summary: Show python modules dependency graph and static memory usage.
Home-page: https://github.com/guyskk/module_graph
Author: guyskk
Author-email: guyskk@qq.com
License: UNKNOWN
Keywords: module dependency graph memory
Platform: UNKNOWN
Classifier: Development Status :: 3 - Alpha
Classifier: Intended Audience :: Developers
Classifier: Topic :: Software Development :: Build Tools
Classifier: License :: OSI Approved :: MIT License
Classifier: Programming Language :: Python :: 3
Classifier: Programming Language :: Python :: 3.5
Classifier: Programming Language :: Python :: 3.6
Classifier: Programming Language :: Python :: 3.7
Requires-Python: >=3.4, <4
Provides-Extra: all
